py4uview/__init__.py
py4uview/reader.py
py4uview/uview.py
py4uview-0.0.6.dist-info/LICENSE
py4uview-0.0.6.dist-info/METADATA
py4uview-0.0.6.dist-info/WHEEL
py4uview-0.0.6.dist-info/top_level.txt
py4uview-0.0.6.dist-info/RECORD
