Metadata-Version: 2.1
Name: py4uview
Version: 0.0.6
Summary: Data analysis package for MAXPEEM
Home-page: https://gitlab.maxiv.lu.se/zhulin/py4uview
Author: Lin Zhu
Author-email: lin.zhu@maxiv.lu.se
Project-URL: Bug Tracker, https://gitlab.maxiv.lu.se/zhulin/py4uview/-/issues
Classifier: Programming Language :: Python :: 3
Classifier: License :: OSI Approved :: GNU Lesser General Public License v3 (LGPLv3)
Classifier: Operating System :: OS Independent
Requires-Python: >=3.9
License-File: LICENSE
Requires-Dist: numpy
Requires-Dist: matplotlib
Requires-Dist: scipy
Requires-Dist: xarray
